{
  "gray04": "#4b4a4d",
  "gray07": "#727075", // Text
  "gray09": "#9b959d", // Comment
  "gray0c": "#cbc9ce",
  "gray0d": "#d9d7dc",
  "gray0e": "#e9e9ef",
  "gray0f": "#f5f5f7",
  "white": "#ffffff", // Background
  "gren": "#a7b386",
  "greenLight": "#d3d9c2",
  "greenLighter": "#e9ece1",
  "greenContrast": "#5a7f24",
  "teal": "#5b9a8b",
  "tealLight": "#adccc5",
  "tealLighter": "#d6e6e2",
  "tealContrast": "#3f7d6c",
  "blue": "#80a4be",
  "blueLight": "#bfd1de",
  "blueLighter": "#dfe8ef",
  "blueContrast": "#4e7997",
  "purple": "#af9fc7",
  "purpleLight": "#d7cfe3",
  "purpleLighter": "#ebe7f1",
  "purpleContrast": "#856caa",
  "red": "#cc5c52",
  "redLight": "#e5ada8",
  "redLighter": "#f3dcda",
  "redContrast": "#bc5248",
  "orange": "#de9e59",
  "orangeLight": "#eeceac",
  "orangeLighter": "#f7e7d5",
  "orangeContrast": "#9f6221",
  "yellow": "#e6c565",
  "yellowLight": "#e9d9a8",
  "yellowLighter": "#f7f0de",
  "yellowContrast": "#ac9032",
  "brightPink": "#ef6c9c",
  "brightPinkLight": "#fae1ea",
  "brightYellow": "#faebaf",
  "brightYellowLight": "#fdf7e1"
}
